jeomaechu/__init__.py
jeomaechu/cli.py
jeomaechu/core.py
jeomaechu/data.py
jeomaechu-0.1.8.dist-info/METADATA
jeomaechu-0.1.8.dist-info/WHEEL
jeomaechu-0.1.8.dist-info/entry_points.txt
jeomaechu-0.1.8.dist-info/licenses/LICENSE
jeomaechu-0.1.8.dist-info/licenses/NOTICE
jeomaechu-0.1.8.dist-info/licenses/NOTICE.md
jeomaechu-0.1.8.dist-info/licenses/NOTICE_ko.md
jeomaechu-0.1.8.dist-info/RECORD
