Metadata-Version: 2.4
Name: jeomaechu
Version: 0.1.8
Summary: A professional lunch menu recommendation (Jeom-Mae-Chu) package for undecided souls.
Project-URL: Homepage, https://rheehose.com
Project-URL: Repository, https://github.com/hslcrb/pypack_jeomaechu
Author-email: "Rheehose (Rhee Creative)" <rheehose@rheehose.com>
License: MIT
License-File: LICENSE
License-File: NOTICE
License-File: NOTICE.md
License-File: NOTICE_ko.md
Keywords: food,jeomaechu,korean,lunch,recommendation
Classifier: License :: OSI Approved :: MIT License
Classifier: Operating System :: OS Independent
Classifier: Programming Language :: Python :: 3
Requires-Python: >=3.9
Requires-Dist: rich>=13.0.0
Requires-Dist: typer>=0.9.0
